README.md
setup.py
src/testgear_adapter_robotframework/TMSLibrary.py
src/testgear_adapter_robotframework/__init__.py
src/testgear_adapter_robotframework/listeners.py
src/testgear_adapter_robotframework/models.py
src/testgear_adapter_robotframework/utils.py
src/testgear_adapter_robotframework.egg-info/PKG-INFO
src/testgear_adapter_robotframework.egg-info/SOURCES.txt
src/testgear_adapter_robotframework.egg-info/dependency_links.txt
src/testgear_adapter_robotframework.egg-info/requires.txt
src/testgear_adapter_robotframework.egg-info/top_level.txt