Metadata-Version: 2.1
Name: testgear-adapter-robotframework
Version: 2.2.0
Summary: Robot Framework adapter for Test Gear
Home-page: https://github.com/testgear-tms/adapters-python/
Author: Integration team
Author-email: integrations@test-gear.io
License: Apache-2.0
Classifier: Programming Language :: Python :: 3
Classifier: Programming Language :: Python :: 3.6
Classifier: Programming Language :: Python :: 3.7
Classifier: Programming Language :: Python :: 3.8
Classifier: Programming Language :: Python :: 3.9
Classifier: Programming Language :: Python :: 3.10
Classifier: Programming Language :: Python :: 3.11
Classifier: Programming Language :: Python :: 3.12
Requires-Dist: attrs
Requires-Dist: robotframework
Requires-Dist: testgear-python-commons==2.2.0
